{
    "name": "github_matrix_report_generator",
    "code": "import os\nimport datetime\n\n# Configuration\nRESULTS_DIR = \"results\"\nOUTPUT_FILE = \"COMPATIBILITY.md\"\n\ndef generate_report():\n    \"\"\"\n    Parses status files from a matrix build and generates a Markdown compatibility table.\n    \n    EXPECTED FILE STRUCTURE:\n    results/\n      result-ubuntu-latest-3.9/status.txt\n      result-ubuntu-latest-3.10/status.txt\n      ...\n    \"\"\"\n    os_list = [\"ubuntu-latest\", \"windows-latest\", \"macos-latest\"]\n    py_versions = [\"3.9\", \"3.10\", \"3.11\", \"3.12\"]\n    \n    table_data = {}\n    \n    for os_name in os_list:\n        for py_ver in py_versions:\n            path = os.path.join(RESULTS_DIR, f\"result-{os_name}-{py_ver}\", \"status.txt\")\n            if os.path.exists(path):\n                with open(path, \"r\", encoding=\"utf-8\") as f:\n                    status = f.read().strip()\n                table_data[(os_name, py_ver)] = \"✅ Pass\" if status == \"Pass\" else \"❌ Fail\"\n            else:\n                table_data[(os_name, py_ver)] = \"⏳ N/A\"\n\n    # Build Markdown\n    header = \"# LogicHive Compatibility Registry\\n\\n\"\n    header += f\"Last Updated: {datetime.datetime.now().strftime('%Y-%m-%d %H:%M:%S')}\\n\\n\"\n    \n    table = \"| OS | \" + \" | \".join([f\"Python {v}\" for v in py_versions]) + \" |\\n\"\n    table += \"|:---| \" + \" | \".join([\":---:\"] * len(py_versions)) + \" |\\n\"\n    \n    for os_name in os_list:\n        row = f\"| **{os_name}** | \"\n        row += \" | \".join([table_data.get((os_name, v), \"⏳ N/A\") for v in py_versions])\n        row += \" |\\n\"\n        table += row\n\n    footer = \"\\n*This report is automatically generated by GitHub Actions.*\\n\"\n    \n    with open(OUTPUT_FILE, \"w\", encoding=\"utf-8\") as f:\n        f.write(header + table + footer)\n\nif __name__ == \"__main__\":\n    generate_report()\n",
    "description": "A specialized utility for GitHub Actions to aggregate matrix build test results into a sleek, readable Markdown compatibility report. Parses 'status.txt' artifacts from multiple jobs and generates a formatted table. Ideal for radiating system health and ensuring transparency in cross-platform releases.",
    "language": "python",
    "tags": [
        "github-actions",
        "ci-cd",
        "observability",
        "markdown"
    ],
    "reliability_score": 0.94,
    "code_hash": "829afb96520732ef15fca4a8ec4d77b063212cdfe1e77d1e12063e0de3573eae",
    "dependencies": [
        "os",
        "datetime"
    ],
    "test_code": "import pytest\nimport os\nimport shutil\n\ndef test_report_generation(tmp_path):\n    # Setup mock results directory\n    results_dir = tmp_path / \"results\"\n    results_dir.mkdir()\n    \n    # Create mock status files\n    job_dir = results_dir / \"result-ubuntu-latest-3.10\"\n    job_dir.mkdir()\n    (job_dir / \"status.txt\").write_text(\"Pass\")\n    \n    # Change CWD for test\n    old_cwd = os.getcwd()\n    os.chdir(tmp_path)\n    \n    try:\n        from github_matrix_report_generator import generate_report\n        generate_report()\n        \n        # Verify output\n        assert os.path.exists(\"COMPATIBILITY.md\")\n        with open(\"COMPATIBILITY.md\", \"r\") as f:\n            content = f.read()\n            assert \"| **ubuntu-latest** |\" in content\n            assert \"✅ Pass\" in content\n    finally:\n        os.chdir(old_cwd)\n"
}